tradukoj/__init__.py
tradukoj/admin.py
tradukoj/apps.py
tradukoj/classviews.py
tradukoj/drf_fields.py
tradukoj/fields.py
tradukoj/models.py
tradukoj/serializers.py
tradukoj/signals.py
tradukoj/tests.py
tradukoj/urls.py
tradukoj/views.py
tradukoj/management/__init__.py
tradukoj/management/commands/__init__.py
tradukoj/management/commands/_private.py
tradukoj/management/commands/destroy_dbkeys_not_in_pofile.py
tradukoj/management/commands/generate_pofile.py
tradukoj/management/commands/show_incompatible_tree_key.py
tradukoj/migrations/0001_initial.py
tradukoj/migrations/0002_auto_20180516_0958.py
tradukoj/migrations/0003_auto_20180516_1859.py
tradukoj/migrations/0004_auto_20180516_1956.py
tradukoj/migrations/0005_auto_20180518_1041.py
tradukoj/migrations/0006_bcp47_direction.py
tradukoj/migrations/0007_bcp47_default.py
tradukoj/migrations/0008_auto_20181213_1238.py
tradukoj/migrations/0008_pre_switch_namespace_field.py
tradukoj/migrations/0009_auto_20181213_1239.py
tradukoj/migrations/0010_auto_20181213_1245.py
tradukoj/migrations/0011_auto_20181213_1322.py
tradukoj/migrations/0012_auto_20181219_1842.py
tradukoj/migrations/0013_auto_20190122_1653.py
tradukoj/migrations/__init__.py
django_tradukoj-1.2.4.dist-info/LICENSE
django_tradukoj-1.2.4.dist-info/METADATA
django_tradukoj-1.2.4.dist-info/WHEEL
django_tradukoj-1.2.4.dist-info/top_level.txt
django_tradukoj-1.2.4.dist-info/RECORD
