Metadata-Version: 2.1
Name: django-tradukoj
Version: 1.2.4
Summary: A django IETF's BCP 47 DB-based translation system
Home-page: https://github.com/develatio/django-tradukoj/
Author: Develatio Technologies S.L.
Author-email: contacto@develat.io
License: BSD
Platform: UNKNOWN
Classifier: Development Status :: 5 - Production/Stable
Classifier: Environment :: Web Environment
Classifier: Framework :: Django
Classifier: Intended Audience :: Developers
Classifier: Intended Audience :: System Administrators
Classifier: License :: OSI Approved :: BSD License
Classifier: Operating System :: OS Independent
Classifier: Programming Language :: Python
Classifier: Programming Language :: Python :: 3.6
Classifier: Programming Language :: Python :: 3.7
Classifier: Topic :: Software Development :: Internationalization
Classifier: Topic :: Software Development :: Localization
Classifier: Topic :: Internet :: WWW/HTTP
Classifier: Topic :: Internet :: WWW/HTTP :: Dynamic Content
Classifier: Topic :: Software Development :: Libraries :: Application Frameworks
Requires-Python: >=3.6.0
Requires-Dist: Django (>=2.0)
Requires-Dist: langcodes (>=1.4.1)
